candy_board_amt/__init__.py
candy_board_amt-1.2.0.dist-info/DESCRIPTION.rst
candy_board_amt-1.2.0.dist-info/METADATA
candy_board_amt-1.2.0.dist-info/RECORD
candy_board_amt-1.2.0.dist-info/WHEEL
candy_board_amt-1.2.0.dist-info/metadata.json
candy_board_amt-1.2.0.dist-info/top_level.txt
