Metadata-Version: 2.0
Name: candy-board-amt
Version: 1.2.0
Summary: Base CANDY LINE boards service for AM Telecom Modules
Home-page: http://github.com/CANDY-LINE/candy-board-amt
Author: Daisuke Baba
Author-email: baba.daisuke@gmail.com
License: BSD3
Download-URL: https://github.com/CANDY-LINE/candy-board-amt/tarball/1.2.0
Keywords: CANDY EGG,CANDY LINE
Platform: UNKNOWN
Classifier: Programming Language :: Python
Classifier: Development Status :: 5 - Production/Stable
Classifier: Natural Language :: English
Classifier: Environment :: Console
Classifier: Intended Audience :: System Administrators
Classifier: Intended Audience :: Developers
Classifier: License :: OSI Approved :: BSD License
Classifier: Operating System :: POSIX :: Linux
Classifier: Topic :: System :: Hardware
